{
  "/_not-found": "app/_not-found.js",
  "/chat/page": "app/chat/page.js",
  "/conversation-history/page": "app/conversation-history/page.js",
  "/marketing/page": "app/marketing/page.js",
  "/page": "app/page.js",
  "/google/page": "app/google/page.js",
  "/pdf/page": "app/pdf/page.js",
  "/keyword-generator/page": "app/keyword-generator/page.js",
  "/sin-nombre/page": "app/sin-nombre/page.js",
  "/perfil/page": "app/perfil/page.js",
  "/prompts/page": "app/prompts/page.js",
  "/subscription-plans/page": "app/subscription-plans/page.js",
  "/tutor/page": "app/tutor/page.js",
  "/youtube/page": "app/youtube/page.js"
}